<annotation>
	<folder>Image</folder>
	<filename>pet71.png</filename>
	<path>/Users/hogbal/Desktop/google drive/RUP/Image/pet71.png</path>
	<source>
		<database>Unknown</database>
	</source>
	<size>
		<width>640</width>
		<height>640</height>
		<depth>3</depth>
	</size>
	<segmented>0</segmented>
	<object>
		<name>pet</name>
		<pose>Unspecified</pose>
		<truncated>0</truncated>
		<difficult>0</difficult>
		<bndbox>
			<xmin>204</xmin>
			<ymin>297</ymin>
			<xmax>290</xmax>
			<ymax>376</ymax>
		</bndbox>
	</object>
	<object>
		<name>pet</name>
		<pose>Unspecified</pose>
		<truncated>0</truncated>
		<difficult>0</difficult>
		<bndbox>
			<xmin>293</xmin>
			<ymin>274</ymin>
			<xmax>373</xmax>
			<ymax>352</ymax>
		</bndbox>
	</object>
	<object>
		<name>pet</name>
		<pose>Unspecified</pose>
		<truncated>0</truncated>
		<difficult>0</difficult>
		<bndbox>
			<xmin>365</xmin>
			<ymin>250</ymin>
			<xmax>461</xmax>
			<ymax>332</ymax>
		</bndbox>
	</object>
</annotation>
